{"frames": {

"blueAirport.png":
{
	"frame": {"x":15,"y":720,"w":15,"h":15},
	"rotated": false,
	"trimmed": false,
	"spriteSourceSize": {"x":0,"y":0,"w":15,"h":15},
	"sourceSize": {"w":15,"h":15}
},
"blueCity.png":
{
	"frame": {"x":15,"y":735,"w":15,"h":15},
	"rotated": false,
	"trimmed": false,
	"spriteSourceSize": {"x":0,"y":0,"w":15,"h":15},
	"sourceSize": {"w":15,"h":15}
},
"blueFactory.png":
{
	"frame": {"x":0,"y":735,"w":15,"h":15},
	"rotated": false,
	"trimmed": false,
	"spriteSourceSize": {"x":0,"y":0,"w":15,"h":15},
	"sourceSize": {"w":15,"h":15}
},
"blueHabor.png":
{
	"frame": {"x":0,"y":720,"w":15,"h":15},
	"rotated": false,
	"trimmed": false,
	"spriteSourceSize": {"x":0,"y":0,"w":15,"h":15},
	"sourceSize": {"w":15,"h":15}
},
"blueMainCity.png":
{
	"frame": {"x":15,"y":1192,"w":15,"h":30},
	"rotated": false,
	"trimmed": false,
	"spriteSourceSize": {"x":0,"y":0,"w":15,"h":30},
	"sourceSize": {"w":15,"h":30}
},
"blueSnowAirport.png":
{
	"frame": {"x":15,"y":705,"w":15,"h":15},
	"rotated": false,
	"trimmed": false,
	"spriteSourceSize": {"x":0,"y":0,"w":15,"h":15},
	"sourceSize": {"w":15,"h":15}
},
"blueSnowCity.png":
{
	"frame": {"x":15,"y":690,"w":15,"h":15},
	"rotated": false,
	"trimmed": false,
	"spriteSourceSize": {"x":0,"y":0,"w":15,"h":15},
	"sourceSize": {"w":15,"h":15}
},
"blueSnowFactory.png":
{
	"frame": {"x":0,"y":690,"w":15,"h":15},
	"rotated": false,
	"trimmed": false,
	"spriteSourceSize": {"x":0,"y":0,"w":15,"h":15},
	"sourceSize": {"w":15,"h":15}
},
"blueSnowHabor.png":
{
	"frame": {"x":0,"y":750,"w":15,"h":15},
	"rotated": false,
	"trimmed": false,
	"spriteSourceSize": {"x":0,"y":0,"w":15,"h":15},
	"sourceSize": {"w":15,"h":15}
},
"blueSnowMainCity.png":
{
	"frame": {"x":0,"y":1192,"w":15,"h":30},
	"rotated": false,
	"trimmed": false,
	"spriteSourceSize": {"x":0,"y":0,"w":15,"h":30},
	"sourceSize": {"w":15,"h":30}
},
"bridgeRight.png":
{
	"frame": {"x":15,"y":750,"w":15,"h":15},
	"rotated": false,
	"trimmed": false,
	"spriteSourceSize": {"x":0,"y":0,"w":15,"h":15},
	"sourceSize": {"w":15,"h":15}
},
"bridgeSnowRight.png":
{
	"frame": {"x":15,"y":795,"w":15,"h":15},
	"rotated": false,
	"trimmed": false,
	"spriteSourceSize": {"x":0,"y":0,"w":15,"h":15},
	"sourceSize": {"w":15,"h":15}
},
"bridgeSnowUp.png":
{
	"frame": {"x":15,"y":810,"w":15,"h":15},
	"rotated": false,
	"trimmed": false,
	"spriteSourceSize": {"x":0,"y":0,"w":15,"h":15},
	"sourceSize": {"w":15,"h":15}
},
"bridgeUp.png":
{
	"frame": {"x":0,"y":810,"w":15,"h":15},
	"rotated": false,
	"trimmed": false,
	"spriteSourceSize": {"x":0,"y":0,"w":15,"h":15},
	"sourceSize": {"w":15,"h":15}
},
"cliff1.png":
{
	"frame": {"x":0,"y":795,"w":15,"h":15},
	"rotated": false,
	"trimmed": false,
	"spriteSourceSize": {"x":0,"y":0,"w":15,"h":15},
	"sourceSize": {"w":15,"h":15}
},
"cliff2.png":
{
	"frame": {"x":15,"y":675,"w":15,"h":15},
	"rotated": false,
	"trimmed": false,
	"spriteSourceSize": {"x":0,"y":0,"w":15,"h":15},
	"sourceSize": {"w":15,"h":15}
},
"cliff3.png":
{
	"frame": {"x":15,"y":585,"w":15,"h":15},
	"rotated": false,
	"trimmed": false,
	"spriteSourceSize": {"x":0,"y":0,"w":15,"h":15},
	"sourceSize": {"w":15,"h":15}
},
"cliff4.png":
{
	"frame": {"x":15,"y":600,"w":15,"h":15},
	"rotated": false,
	"trimmed": false,
	"spriteSourceSize": {"x":0,"y":0,"w":15,"h":15},
	"sourceSize": {"w":15,"h":15}
},
"cliff5.png":
{
	"frame": {"x":0,"y":600,"w":15,"h":15},
	"rotated": false,
	"trimmed": false,
	"spriteSourceSize": {"x":0,"y":0,"w":15,"h":15},
	"sourceSize": {"w":15,"h":15}
},
"cliff6.png":
{
	"frame": {"x":0,"y":585,"w":15,"h":15},
	"rotated": false,
	"trimmed": false,
	"spriteSourceSize": {"x":0,"y":0,"w":15,"h":15},
	"sourceSize": {"w":15,"h":15}
},
"cliff7.png":
{
	"frame": {"x":15,"y":570,"w":15,"h":15},
	"rotated": false,
	"trimmed": false,
	"spriteSourceSize": {"x":0,"y":0,"w":15,"h":15},
	"sourceSize": {"w":15,"h":15}
},
"cliff8.png":
{
	"frame": {"x":15,"y":555,"w":15,"h":15},
	"rotated": false,
	"trimmed": false,
	"spriteSourceSize": {"x":0,"y":0,"w":15,"h":15},
	"sourceSize": {"w":15,"h":15}
},
"cliff9.png":
{
	"frame": {"x":0,"y":555,"w":15,"h":15},
	"rotated": false,
	"trimmed": false,
	"spriteSourceSize": {"x":0,"y":0,"w":15,"h":15},
	"sourceSize": {"w":15,"h":15}
},
"cliff10.png":
{
	"frame": {"x":15,"y":780,"w":15,"h":15},
	"rotated": false,
	"trimmed": false,
	"spriteSourceSize": {"x":0,"y":0,"w":15,"h":15},
	"sourceSize": {"w":15,"h":15}
},
"cliff11.png":
{
	"frame": {"x":0,"y":765,"w":15,"h":15},
	"rotated": false,
	"trimmed": false,
	"spriteSourceSize": {"x":0,"y":0,"w":15,"h":15},
	"sourceSize": {"w":15,"h":15}
},
"cliff12.png":
{
	"frame": {"x":0,"y":780,"w":15,"h":15},
	"rotated": false,
	"trimmed": false,
	"spriteSourceSize": {"x":0,"y":0,"w":15,"h":15},
	"sourceSize": {"w":15,"h":15}
},
"cliff13.png":
{
	"frame": {"x":15,"y":765,"w":15,"h":15},
	"rotated": false,
	"trimmed": false,
	"spriteSourceSize": {"x":0,"y":0,"w":15,"h":15},
	"sourceSize": {"w":15,"h":15}
},
"cliff14.png":
{
	"frame": {"x":0,"y":705,"w":15,"h":15},
	"rotated": false,
	"trimmed": false,
	"spriteSourceSize": {"x":0,"y":0,"w":15,"h":15},
	"sourceSize": {"w":15,"h":15}
},
"cliffSnow1.png":
{
	"frame": {"x":0,"y":615,"w":15,"h":15},
	"rotated": false,
	"trimmed": false,
	"spriteSourceSize": {"x":0,"y":0,"w":15,"h":15},
	"sourceSize": {"w":15,"h":15}
},
"cliffSnow2.png":
{
	"frame": {"x":15,"y":645,"w":15,"h":15},
	"rotated": false,
	"trimmed": false,
	"spriteSourceSize": {"x":0,"y":0,"w":15,"h":15},
	"sourceSize": {"w":15,"h":15}
},
"cliffSnow3.png":
{
	"frame": {"x":0,"y":645,"w":15,"h":15},
	"rotated": false,
	"trimmed": false,
	"spriteSourceSize": {"x":0,"y":0,"w":15,"h":15},
	"sourceSize": {"w":15,"h":15}
},
"cliffSnow4.png":
{
	"frame": {"x":0,"y":630,"w":15,"h":15},
	"rotated": false,
	"trimmed": false,
	"spriteSourceSize": {"x":0,"y":0,"w":15,"h":15},
	"sourceSize": {"w":15,"h":15}
},
"cliffSnow5.png":
{
	"frame": {"x":15,"y":615,"w":15,"h":15},
	"rotated": false,
	"trimmed": false,
	"spriteSourceSize": {"x":0,"y":0,"w":15,"h":15},
	"sourceSize": {"w":15,"h":15}
},
"cliffSnow6.png":
{
	"frame": {"x":0,"y":570,"w":15,"h":15},
	"rotated": false,
	"trimmed": false,
	"spriteSourceSize": {"x":0,"y":0,"w":15,"h":15},
	"sourceSize": {"w":15,"h":15}
},
"cliffSnow7.png":
{
	"frame": {"x":0,"y":840,"w":15,"h":15},
	"rotated": false,
	"trimmed": false,
	"spriteSourceSize": {"x":0,"y":0,"w":15,"h":15},
	"sourceSize": {"w":15,"h":15}
},
"cliffSnow8.png":
{
	"frame": {"x":0,"y":990,"w":15,"h":15},
	"rotated": false,
	"trimmed": false,
	"spriteSourceSize": {"x":0,"y":0,"w":15,"h":15},
	"sourceSize": {"w":15,"h":15}
},
"cliffSnow9.png":
{
	"frame": {"x":0,"y":1005,"w":15,"h":15},
	"rotated": false,
	"trimmed": false,
	"spriteSourceSize": {"x":0,"y":0,"w":15,"h":15},
	"sourceSize": {"w":15,"h":15}
},
"cliffSnow10.png":
{
	"frame": {"x":15,"y":630,"w":15,"h":15},
	"rotated": false,
	"trimmed": false,
	"spriteSourceSize": {"x":0,"y":0,"w":15,"h":15},
	"sourceSize": {"w":15,"h":15}
},
"cliffSnow11.png":
{
	"frame": {"x":0,"y":660,"w":15,"h":15},
	"rotated": false,
	"trimmed": false,
	"spriteSourceSize": {"x":0,"y":0,"w":15,"h":15},
	"sourceSize": {"w":15,"h":15}
},
"cliffSnow12.png":
{
	"frame": {"x":0,"y":675,"w":15,"h":15},
	"rotated": false,
	"trimmed": false,
	"spriteSourceSize": {"x":0,"y":0,"w":15,"h":15},
	"sourceSize": {"w":15,"h":15}
},
"cliffSnow13.png":
{
	"frame": {"x":0,"y":825,"w":15,"h":15},
	"rotated": false,
	"trimmed": false,
	"spriteSourceSize": {"x":0,"y":0,"w":15,"h":15},
	"sourceSize": {"w":15,"h":15}
},
"cliffSnow14.png":
{
	"frame": {"x":15,"y":660,"w":15,"h":15},
	"rotated": false,
	"trimmed": false,
	"spriteSourceSize": {"x":0,"y":0,"w":15,"h":15},
	"sourceSize": {"w":15,"h":15}
},
"deepSea.png":
{
	"frame": {"x":15,"y":990,"w":15,"h":15},
	"rotated": false,
	"trimmed": false,
	"spriteSourceSize": {"x":0,"y":0,"w":15,"h":15},
	"sourceSize": {"w":15,"h":15}
},
"deepSeaSnow.png":
{
	"frame": {"x":15,"y":975,"w":15,"h":15},
	"rotated": false,
	"trimmed": false,
	"spriteSourceSize": {"x":0,"y":0,"w":15,"h":15},
	"sourceSize": {"w":15,"h":15}
},
"explosionArea.png":
{
	"frame": {"x":15,"y":1005,"w":15,"h":15},
	"rotated": false,
	"trimmed": false,
	"spriteSourceSize": {"x":0,"y":0,"w":15,"h":15},
	"sourceSize": {"w":15,"h":15}
},
"freeAirport.png":
{
	"frame": {"x":0,"y":960,"w":15,"h":15},
	"rotated": false,
	"trimmed": false,
	"spriteSourceSize": {"x":0,"y":0,"w":15,"h":15},
	"sourceSize": {"w":15,"h":15}
},
"freeCity.png":
{
	"frame": {"x":15,"y":945,"w":15,"h":15},
	"rotated": false,
	"trimmed": false,
	"spriteSourceSize": {"x":0,"y":0,"w":15,"h":15},
	"sourceSize": {"w":15,"h":15}
},
"freeFactory.png":
{
	"frame": {"x":15,"y":960,"w":15,"h":15},
	"rotated": false,
	"trimmed": false,
	"spriteSourceSize": {"x":0,"y":0,"w":15,"h":15},
	"sourceSize": {"w":15,"h":15}
},
"freeHabor.png":
{
	"frame": {"x":0,"y":1050,"w":15,"h":15},
	"rotated": false,
	"trimmed": false,
	"spriteSourceSize": {"x":0,"y":0,"w":15,"h":15},
	"sourceSize": {"w":15,"h":15}
},
"freeSnowAirport.png":
{
	"frame": {"x":0,"y":1020,"w":15,"h":15},
	"rotated": false,
	"trimmed": false,
	"spriteSourceSize": {"x":0,"y":0,"w":15,"h":15},
	"sourceSize": {"w":15,"h":15}
},
"freeSnowCity.png":
{
	"frame": {"x":0,"y":1035,"w":15,"h":15},
	"rotated": false,
	"trimmed": false,
	"spriteSourceSize": {"x":0,"y":0,"w":15,"h":15},
	"sourceSize": {"w":15,"h":15}
},
"freeSnowFactory.png":
{
	"frame": {"x":15,"y":1020,"w":15,"h":15},
	"rotated": false,
	"trimmed": false,
	"spriteSourceSize": {"x":0,"y":0,"w":15,"h":15},
	"sourceSize": {"w":15,"h":15}
},
"freeSnowHabor.png":
{
	"frame": {"x":15,"y":1035,"w":15,"h":15},
	"rotated": false,
	"trimmed": false,
	"spriteSourceSize": {"x":0,"y":0,"w":15,"h":15},
	"sourceSize": {"w":15,"h":15}
},
"grass.png":
{
	"frame": {"x":0,"y":975,"w":15,"h":15},
	"rotated": false,
	"trimmed": false,
	"spriteSourceSize": {"x":0,"y":0,"w":15,"h":15},
	"sourceSize": {"w":15,"h":15}
},
"grassSnow.png":
{
	"frame": {"x":15,"y":840,"w":15,"h":15},
	"rotated": false,
	"trimmed": false,
	"spriteSourceSize": {"x":0,"y":0,"w":15,"h":15},
	"sourceSize": {"w":15,"h":15}
},
"greenAirport.png":
{
	"frame": {"x":0,"y":870,"w":15,"h":15},
	"rotated": false,
	"trimmed": false,
	"spriteSourceSize": {"x":0,"y":0,"w":15,"h":15},
	"sourceSize": {"w":15,"h":15}
},
"greenCity.png":
{
	"frame": {"x":15,"y":855,"w":15,"h":15},
	"rotated": false,
	"trimmed": false,
	"spriteSourceSize": {"x":0,"y":0,"w":15,"h":15},
	"sourceSize": {"w":15,"h":15}
},
"greenFactory.png":
{
	"frame": {"x":15,"y":870,"w":15,"h":15},
	"rotated": false,
	"trimmed": false,
	"spriteSourceSize": {"x":0,"y":0,"w":15,"h":15},
	"sourceSize": {"w":15,"h":15}
},
"greenHabor.png":
{
	"frame": {"x":0,"y":855,"w":15,"h":15},
	"rotated": false,
	"trimmed": false,
	"spriteSourceSize": {"x":0,"y":0,"w":15,"h":15},
	"sourceSize": {"w":15,"h":15}
},
"greenMainCity.png":
{
	"frame": {"x":15,"y":1135,"w":15,"h":27},
	"rotated": false,
	"trimmed": false,
	"spriteSourceSize": {"x":0,"y":0,"w":15,"h":27},
	"sourceSize": {"w":15,"h":27}
},
"greenSnowAirport.png":
{
	"frame": {"x":0,"y":945,"w":15,"h":15},
	"rotated": false,
	"trimmed": false,
	"spriteSourceSize": {"x":0,"y":0,"w":15,"h":15},
	"sourceSize": {"w":15,"h":15}
},
"greenSnowCity.png":
{
	"frame": {"x":15,"y":825,"w":15,"h":15},
	"rotated": false,
	"trimmed": false,
	"spriteSourceSize": {"x":0,"y":0,"w":15,"h":15},
	"sourceSize": {"w":15,"h":15}
},
"greenSnowFactory.png":
{
	"frame": {"x":0,"y":885,"w":15,"h":15},
	"rotated": false,
	"trimmed": false,
	"spriteSourceSize": {"x":0,"y":0,"w":15,"h":15},
	"sourceSize": {"w":15,"h":15}
},
"greenSnowHabor.png":
{
	"frame": {"x":15,"y":900,"w":15,"h":15},
	"rotated": false,
	"trimmed": false,
	"spriteSourceSize": {"x":0,"y":0,"w":15,"h":15},
	"sourceSize": {"w":15,"h":15}
},
"greenSnowMainCity.png":
{
	"frame": {"x":0,"y":1135,"w":15,"h":27},
	"rotated": false,
	"trimmed": false,
	"spriteSourceSize": {"x":0,"y":0,"w":15,"h":27},
	"sourceSize": {"w":15,"h":27}
},
"hill.png":
{
	"frame": {"x":0,"y":930,"w":15,"h":15},
	"rotated": false,
	"trimmed": false,
	"spriteSourceSize": {"x":0,"y":0,"w":15,"h":15},
	"sourceSize": {"w":15,"h":15}
},
"hillSnow.png":
{
	"frame": {"x":15,"y":915,"w":15,"h":15},
	"rotated": false,
	"trimmed": false,
	"spriteSourceSize": {"x":0,"y":0,"w":15,"h":15},
	"sourceSize": {"w":15,"h":15}
},
"mountainSnow.png":
{
	"frame": {"x":0,"y":1114,"w":15,"h":21},
	"rotated": false,
	"trimmed": false,
	"spriteSourceSize": {"x":0,"y":0,"w":15,"h":21},
	"sourceSize": {"w":15,"h":21}
},
"moutain.png":
{
	"frame": {"x":15,"y":1114,"w":15,"h":21},
	"rotated": false,
	"trimmed": false,
	"spriteSourceSize": {"x":0,"y":0,"w":15,"h":21},
	"sourceSize": {"w":15,"h":21}
},
"moveableArea.png":
{
	"frame": {"x":15,"y":930,"w":15,"h":15},
	"rotated": false,
	"trimmed": false,
	"spriteSourceSize": {"x":0,"y":0,"w":15,"h":15},
	"sourceSize": {"w":15,"h":15}
},
"redAirport.png":
{
	"frame": {"x":0,"y":915,"w":15,"h":15},
	"rotated": false,
	"trimmed": false,
	"spriteSourceSize": {"x":0,"y":0,"w":15,"h":15},
	"sourceSize": {"w":15,"h":15}
},
"redCity.png":
{
	"frame": {"x":0,"y":900,"w":15,"h":15},
	"rotated": false,
	"trimmed": false,
	"spriteSourceSize": {"x":0,"y":0,"w":15,"h":15},
	"sourceSize": {"w":15,"h":15}
},
"redFactory.png":
{
	"frame": {"x":15,"y":885,"w":15,"h":15},
	"rotated": false,
	"trimmed": false,
	"spriteSourceSize": {"x":0,"y":0,"w":15,"h":15},
	"sourceSize": {"w":15,"h":15}
},
"redHabor.png":
{
	"frame": {"x":0,"y":15,"w":15,"h":15},
	"rotated": false,
	"trimmed": false,
	"spriteSourceSize": {"x":0,"y":0,"w":15,"h":15},
	"sourceSize": {"w":15,"h":15}
},
"redMainCity.png":
{
	"frame": {"x":15,"y":1222,"w":15,"h":30},
	"rotated": false,
	"trimmed": false,
	"spriteSourceSize": {"x":0,"y":0,"w":15,"h":30},
	"sourceSize": {"w":15,"h":30}
},
"redSnowAirPort.png":
{
	"frame": {"x":15,"y":165,"w":15,"h":15},
	"rotated": false,
	"trimmed": false,
	"spriteSourceSize": {"x":0,"y":0,"w":15,"h":15},
	"sourceSize": {"w":15,"h":15}
},
"redSnowcity.png":
{
	"frame": {"x":15,"y":540,"w":15,"h":15},
	"rotated": false,
	"trimmed": false,
	"spriteSourceSize": {"x":0,"y":0,"w":15,"h":15},
	"sourceSize": {"w":15,"h":15}
},
"redSnowFactory.png":
{
	"frame": {"x":15,"y":180,"w":15,"h":15},
	"rotated": false,
	"trimmed": false,
	"spriteSourceSize": {"x":0,"y":0,"w":15,"h":15},
	"sourceSize": {"w":15,"h":15}
},
"redSnowHabor.png":
{
	"frame": {"x":0,"y":180,"w":15,"h":15},
	"rotated": false,
	"trimmed": false,
	"spriteSourceSize": {"x":0,"y":0,"w":15,"h":15},
	"sourceSize": {"w":15,"h":15}
},
"redSnowMainCity.png":
{
	"frame": {"x":15,"y":1162,"w":15,"h":30},
	"rotated": false,
	"trimmed": false,
	"spriteSourceSize": {"x":0,"y":0,"w":15,"h":30},
	"sourceSize": {"w":15,"h":30}
},
"river1.png":
{
	"frame": {"x":0,"y":165,"w":15,"h":15},
	"rotated": false,
	"trimmed": false,
	"spriteSourceSize": {"x":0,"y":0,"w":15,"h":15},
	"sourceSize": {"w":15,"h":15}
},
"river2.png":
{
	"frame": {"x":15,"y":150,"w":15,"h":15},
	"rotated": false,
	"trimmed": false,
	"spriteSourceSize": {"x":0,"y":0,"w":15,"h":15},
	"sourceSize": {"w":15,"h":15}
},
"river3.png":
{
	"frame": {"x":15,"y":135,"w":15,"h":15},
	"rotated": false,
	"trimmed": false,
	"spriteSourceSize": {"x":0,"y":0,"w":15,"h":15},
	"sourceSize": {"w":15,"h":15}
},
"river4.png":
{
	"frame": {"x":0,"y":135,"w":15,"h":15},
	"rotated": false,
	"trimmed": false,
	"spriteSourceSize": {"x":0,"y":0,"w":15,"h":15},
	"sourceSize": {"w":15,"h":15}
},
"river5.png":
{
	"frame": {"x":0,"y":195,"w":15,"h":15},
	"rotated": false,
	"trimmed": false,
	"spriteSourceSize": {"x":0,"y":0,"w":15,"h":15},
	"sourceSize": {"w":15,"h":15}
},
"river6.png":
{
	"frame": {"x":15,"y":195,"w":15,"h":15},
	"rotated": false,
	"trimmed": false,
	"spriteSourceSize": {"x":0,"y":0,"w":15,"h":15},
	"sourceSize": {"w":15,"h":15}
},
"river7.png":
{
	"frame": {"x":15,"y":240,"w":15,"h":15},
	"rotated": false,
	"trimmed": false,
	"spriteSourceSize": {"x":0,"y":0,"w":15,"h":15},
	"sourceSize": {"w":15,"h":15}
},
"river8.png":
{
	"frame": {"x":15,"y":255,"w":15,"h":15},
	"rotated": false,
	"trimmed": false,
	"spriteSourceSize": {"x":0,"y":0,"w":15,"h":15},
	"sourceSize": {"w":15,"h":15}
},
"riverSnow1.png":
{
	"frame": {"x":0,"y":255,"w":15,"h":15},
	"rotated": false,
	"trimmed": false,
	"spriteSourceSize": {"x":0,"y":0,"w":15,"h":15},
	"sourceSize": {"w":15,"h":15}
},
"riverSnow2.png":
{
	"frame": {"x":0,"y":240,"w":15,"h":15},
	"rotated": false,
	"trimmed": false,
	"spriteSourceSize": {"x":0,"y":0,"w":15,"h":15},
	"sourceSize": {"w":15,"h":15}
},
"riverSnow3.png":
{
	"frame": {"x":15,"y":225,"w":15,"h":15},
	"rotated": false,
	"trimmed": false,
	"spriteSourceSize": {"x":0,"y":0,"w":15,"h":15},
	"sourceSize": {"w":15,"h":15}
},
"riverSnow4.png":
{
	"frame": {"x":0,"y":210,"w":15,"h":15},
	"rotated": false,
	"trimmed": false,
	"spriteSourceSize": {"x":0,"y":0,"w":15,"h":15},
	"sourceSize": {"w":15,"h":15}
},
"riverSnow5.png":
{
	"frame": {"x":0,"y":225,"w":15,"h":15},
	"rotated": false,
	"trimmed": false,
	"spriteSourceSize": {"x":0,"y":0,"w":15,"h":15},
	"sourceSize": {"w":15,"h":15}
},
"riverSnow6.png":
{
	"frame": {"x":15,"y":210,"w":15,"h":15},
	"rotated": false,
	"trimmed": false,
	"spriteSourceSize": {"x":0,"y":0,"w":15,"h":15},
	"sourceSize": {"w":15,"h":15}
},
"riverSnow7.png":
{
	"frame": {"x":0,"y":150,"w":15,"h":15},
	"rotated": false,
	"trimmed": false,
	"spriteSourceSize": {"x":0,"y":0,"w":15,"h":15},
	"sourceSize": {"w":15,"h":15}
},
"riverSnow8.png":
{
	"frame": {"x":15,"y":120,"w":15,"h":15},
	"rotated": false,
	"trimmed": false,
	"spriteSourceSize": {"x":0,"y":0,"w":15,"h":15},
	"sourceSize": {"w":15,"h":15}
},
"road1.png":
{
	"frame": {"x":15,"y":30,"w":15,"h":15},
	"rotated": false,
	"trimmed": false,
	"spriteSourceSize": {"x":0,"y":0,"w":15,"h":15},
	"sourceSize": {"w":15,"h":15}
},
"road2.png":
{
	"frame": {"x":0,"y":30,"w":15,"h":15},
	"rotated": false,
	"trimmed": false,
	"spriteSourceSize": {"x":0,"y":0,"w":15,"h":15},
	"sourceSize": {"w":15,"h":15}
},
"road3.png":
{
	"frame": {"x":15,"y":15,"w":15,"h":15},
	"rotated": false,
	"trimmed": false,
	"spriteSourceSize": {"x":0,"y":0,"w":15,"h":15},
	"sourceSize": {"w":15,"h":15}
},
"road4.png":
{
	"frame": {"x":15,"y":0,"w":15,"h":15},
	"rotated": false,
	"trimmed": false,
	"spriteSourceSize": {"x":0,"y":0,"w":15,"h":15},
	"sourceSize": {"w":15,"h":15}
},
"road5.png":
{
	"frame": {"x":0,"y":0,"w":15,"h":15},
	"rotated": false,
	"trimmed": false,
	"spriteSourceSize": {"x":0,"y":0,"w":15,"h":15},
	"sourceSize": {"w":15,"h":15}
},
"road6.png":
{
	"frame": {"x":0,"y":60,"w":15,"h":15},
	"rotated": false,
	"trimmed": false,
	"spriteSourceSize": {"x":0,"y":0,"w":15,"h":15},
	"sourceSize": {"w":15,"h":15}
},
"road7.png":
{
	"frame": {"x":15,"y":75,"w":15,"h":15},
	"rotated": false,
	"trimmed": false,
	"spriteSourceSize": {"x":0,"y":0,"w":15,"h":15},
	"sourceSize": {"w":15,"h":15}
},
"road8.png":
{
	"frame": {"x":0,"y":105,"w":15,"h":15},
	"rotated": false,
	"trimmed": false,
	"spriteSourceSize": {"x":0,"y":0,"w":15,"h":15},
	"sourceSize": {"w":15,"h":15}
},
"road9.png":
{
	"frame": {"x":0,"y":120,"w":15,"h":15},
	"rotated": false,
	"trimmed": false,
	"spriteSourceSize": {"x":0,"y":0,"w":15,"h":15},
	"sourceSize": {"w":15,"h":15}
},
"road10.png":
{
	"frame": {"x":15,"y":45,"w":15,"h":15},
	"rotated": false,
	"trimmed": false,
	"spriteSourceSize": {"x":0,"y":0,"w":15,"h":15},
	"sourceSize": {"w":15,"h":15}
},
"road11.png":
{
	"frame": {"x":0,"y":45,"w":15,"h":15},
	"rotated": false,
	"trimmed": false,
	"spriteSourceSize": {"x":0,"y":0,"w":15,"h":15},
	"sourceSize": {"w":15,"h":15}
},
"roadSnow1.png":
{
	"frame": {"x":15,"y":105,"w":15,"h":15},
	"rotated": false,
	"trimmed": false,
	"spriteSourceSize": {"x":0,"y":0,"w":15,"h":15},
	"sourceSize": {"w":15,"h":15}
},
"roadSnow2.png":
{
	"frame": {"x":0,"y":75,"w":15,"h":15},
	"rotated": false,
	"trimmed": false,
	"spriteSourceSize": {"x":0,"y":0,"w":15,"h":15},
	"sourceSize": {"w":15,"h":15}
},
"roadSnow3.png":
{
	"frame": {"x":15,"y":60,"w":15,"h":15},
	"rotated": false,
	"trimmed": false,
	"spriteSourceSize": {"x":0,"y":0,"w":15,"h":15},
	"sourceSize": {"w":15,"h":15}
},
"roadSnow4.png":
{
	"frame": {"x":0,"y":270,"w":15,"h":15},
	"rotated": false,
	"trimmed": false,
	"spriteSourceSize": {"x":0,"y":0,"w":15,"h":15},
	"sourceSize": {"w":15,"h":15}
},
"roadSnow5.png":
{
	"frame": {"x":15,"y":285,"w":15,"h":15},
	"rotated": false,
	"trimmed": false,
	"spriteSourceSize": {"x":0,"y":0,"w":15,"h":15},
	"sourceSize": {"w":15,"h":15}
},
"roadSnow6.png":
{
	"frame": {"x":0,"y":450,"w":15,"h":15},
	"rotated": false,
	"trimmed": false,
	"spriteSourceSize": {"x":0,"y":0,"w":15,"h":15},
	"sourceSize": {"w":15,"h":15}
},
"roadSnow7.png":
{
	"frame": {"x":0,"y":465,"w":15,"h":15},
	"rotated": false,
	"trimmed": false,
	"spriteSourceSize": {"x":0,"y":0,"w":15,"h":15},
	"sourceSize": {"w":15,"h":15}
},
"roadSnow8.png":
{
	"frame": {"x":15,"y":450,"w":15,"h":15},
	"rotated": false,
	"trimmed": false,
	"spriteSourceSize": {"x":0,"y":0,"w":15,"h":15},
	"sourceSize": {"w":15,"h":15}
},
"roadSnow9.png":
{
	"frame": {"x":15,"y":435,"w":15,"h":15},
	"rotated": false,
	"trimmed": false,
	"spriteSourceSize": {"x":0,"y":0,"w":15,"h":15},
	"sourceSize": {"w":15,"h":15}
},
"roadSnow10.png":
{
	"frame": {"x":15,"y":90,"w":15,"h":15},
	"rotated": false,
	"trimmed": false,
	"spriteSourceSize": {"x":0,"y":0,"w":15,"h":15},
	"sourceSize": {"w":15,"h":15}
},
"roadSnow11.png":
{
	"frame": {"x":0,"y":90,"w":15,"h":15},
	"rotated": false,
	"trimmed": false,
	"spriteSourceSize": {"x":0,"y":0,"w":15,"h":15},
	"sourceSize": {"w":15,"h":15}
},
"seaShore1.png":
{
	"frame": {"x":0,"y":435,"w":15,"h":15},
	"rotated": false,
	"trimmed": false,
	"spriteSourceSize": {"x":0,"y":0,"w":15,"h":15},
	"sourceSize": {"w":15,"h":15}
},
"seaShore2.png":
{
	"frame": {"x":0,"y":480,"w":15,"h":15},
	"rotated": false,
	"trimmed": false,
	"spriteSourceSize": {"x":0,"y":0,"w":15,"h":15},
	"sourceSize": {"w":15,"h":15}
},
"seaShore3.png":
{
	"frame": {"x":0,"y":525,"w":15,"h":15},
	"rotated": false,
	"trimmed": false,
	"spriteSourceSize": {"x":0,"y":0,"w":15,"h":15},
	"sourceSize": {"w":15,"h":15}
},
"seaShore4.png":
{
	"frame": {"x":0,"y":540,"w":15,"h":15},
	"rotated": false,
	"trimmed": false,
	"spriteSourceSize": {"x":0,"y":0,"w":15,"h":15},
	"sourceSize": {"w":15,"h":15}
},
"seaShore5.png":
{
	"frame": {"x":15,"y":525,"w":15,"h":15},
	"rotated": false,
	"trimmed": false,
	"spriteSourceSize": {"x":0,"y":0,"w":15,"h":15},
	"sourceSize": {"w":15,"h":15}
},
"seaShore6.png":
{
	"frame": {"x":15,"y":510,"w":15,"h":15},
	"rotated": false,
	"trimmed": false,
	"spriteSourceSize": {"x":0,"y":0,"w":15,"h":15},
	"sourceSize": {"w":15,"h":15}
},
"seaShore7.png":
{
	"frame": {"x":0,"y":510,"w":15,"h":15},
	"rotated": false,
	"trimmed": false,
	"spriteSourceSize": {"x":0,"y":0,"w":15,"h":15},
	"sourceSize": {"w":15,"h":15}
},
"seaShore8.png":
{
	"frame": {"x":15,"y":480,"w":15,"h":15},
	"rotated": false,
	"trimmed": false,
	"spriteSourceSize": {"x":0,"y":0,"w":15,"h":15},
	"sourceSize": {"w":15,"h":15}
},
"seaShore9.png":
{
	"frame": {"x":15,"y":495,"w":15,"h":15},
	"rotated": false,
	"trimmed": false,
	"spriteSourceSize": {"x":0,"y":0,"w":15,"h":15},
	"sourceSize": {"w":15,"h":15}
},
"seaShore10.png":
{
	"frame": {"x":0,"y":420,"w":15,"h":15},
	"rotated": false,
	"trimmed": false,
	"spriteSourceSize": {"x":0,"y":0,"w":15,"h":15},
	"sourceSize": {"w":15,"h":15}
},
"seaShore11.png":
{
	"frame": {"x":15,"y":405,"w":15,"h":15},
	"rotated": false,
	"trimmed": false,
	"spriteSourceSize": {"x":0,"y":0,"w":15,"h":15},
	"sourceSize": {"w":15,"h":15}
},
"seaShore12.png":
{
	"frame": {"x":15,"y":465,"w":15,"h":15},
	"rotated": false,
	"trimmed": false,
	"spriteSourceSize": {"x":0,"y":0,"w":15,"h":15},
	"sourceSize": {"w":15,"h":15}
},
"seaShoreSnow1.png":
{
	"frame": {"x":0,"y":495,"w":15,"h":15},
	"rotated": false,
	"trimmed": false,
	"spriteSourceSize": {"x":0,"y":0,"w":15,"h":15},
	"sourceSize": {"w":15,"h":15}
},
"seaShoreSnow2.png":
{
	"frame": {"x":15,"y":420,"w":15,"h":15},
	"rotated": false,
	"trimmed": false,
	"spriteSourceSize": {"x":0,"y":0,"w":15,"h":15},
	"sourceSize": {"w":15,"h":15}
},
"seaShoreSnow3.png":
{
	"frame": {"x":0,"y":405,"w":15,"h":15},
	"rotated": false,
	"trimmed": false,
	"spriteSourceSize": {"x":0,"y":0,"w":15,"h":15},
	"sourceSize": {"w":15,"h":15}
},
"seaShoreSnow4.png":
{
	"frame": {"x":0,"y":315,"w":15,"h":15},
	"rotated": false,
	"trimmed": false,
	"spriteSourceSize": {"x":0,"y":0,"w":15,"h":15},
	"sourceSize": {"w":15,"h":15}
},
"seaShoreSnow5.png":
{
	"frame": {"x":0,"y":330,"w":15,"h":15},
	"rotated": false,
	"trimmed": false,
	"spriteSourceSize": {"x":0,"y":0,"w":15,"h":15},
	"sourceSize": {"w":15,"h":15}
},
"seaShoreSnow6.png":
{
	"frame": {"x":15,"y":315,"w":15,"h":15},
	"rotated": false,
	"trimmed": false,
	"spriteSourceSize": {"x":0,"y":0,"w":15,"h":15},
	"sourceSize": {"w":15,"h":15}
},
"seaShoreSnow7.png":
{
	"frame": {"x":15,"y":300,"w":15,"h":15},
	"rotated": false,
	"trimmed": false,
	"spriteSourceSize": {"x":0,"y":0,"w":15,"h":15},
	"sourceSize": {"w":15,"h":15}
},
"seaShoreSnow8.png":
{
	"frame": {"x":0,"y":1082,"w":15,"h":16},
	"rotated": false,
	"trimmed": false,
	"spriteSourceSize": {"x":0,"y":0,"w":15,"h":16},
	"sourceSize": {"w":15,"h":16}
},
"seaShoreSnow9.png":
{
	"frame": {"x":0,"y":1098,"w":15,"h":16},
	"rotated": false,
	"trimmed": false,
	"spriteSourceSize": {"x":0,"y":0,"w":15,"h":16},
	"sourceSize": {"w":15,"h":16}
},
"seaShoreSnow10.png":
{
	"frame": {"x":0,"y":1066,"w":15,"h":16},
	"rotated": false,
	"trimmed": false,
	"spriteSourceSize": {"x":0,"y":0,"w":15,"h":16},
	"sourceSize": {"w":15,"h":16}
},
"seaShoreSnow11.png":
{
	"frame": {"x":15,"y":1082,"w":15,"h":16},
	"rotated": false,
	"trimmed": false,
	"spriteSourceSize": {"x":0,"y":0,"w":15,"h":16},
	"sourceSize": {"w":15,"h":16}
},
"seaShoreSnow12.png":
{
	"frame": {"x":15,"y":1098,"w":15,"h":16},
	"rotated": false,
	"trimmed": false,
	"spriteSourceSize": {"x":0,"y":0,"w":15,"h":16},
	"sourceSize": {"w":15,"h":16}
},
"silverAirport.png":
{
	"frame": {"x":0,"y":300,"w":15,"h":15},
	"rotated": false,
	"trimmed": false,
	"spriteSourceSize": {"x":0,"y":0,"w":15,"h":15},
	"sourceSize": {"w":15,"h":15}
},
"silverCity.png":
{
	"frame": {"x":0,"y":285,"w":15,"h":15},
	"rotated": false,
	"trimmed": false,
	"spriteSourceSize": {"x":0,"y":0,"w":15,"h":15},
	"sourceSize": {"w":15,"h":15}
},
"silverFactory.png":
{
	"frame": {"x":15,"y":270,"w":15,"h":15},
	"rotated": false,
	"trimmed": false,
	"spriteSourceSize": {"x":0,"y":0,"w":15,"h":15},
	"sourceSize": {"w":15,"h":15}
},
"silverHabor.png":
{
	"frame": {"x":15,"y":330,"w":15,"h":15},
	"rotated": false,
	"trimmed": false,
	"spriteSourceSize": {"x":0,"y":0,"w":15,"h":15},
	"sourceSize": {"w":15,"h":15}
},
"silverMainCity.png":
{
	"frame": {"x":0,"y":1222,"w":15,"h":30},
	"rotated": false,
	"trimmed": false,
	"spriteSourceSize": {"x":0,"y":0,"w":15,"h":30},
	"sourceSize": {"w":15,"h":30}
},
"tree.png":
{
	"frame": {"x":15,"y":1066,"w":15,"h":16},
	"rotated": false,
	"trimmed": false,
	"spriteSourceSize": {"x":0,"y":0,"w":15,"h":16},
	"sourceSize": {"w":15,"h":16}
},
"treeSnow.png":
{
	"frame": {"x":15,"y":1050,"w":15,"h":16},
	"rotated": false,
	"trimmed": false,
	"spriteSourceSize": {"x":0,"y":0,"w":15,"h":16},
	"sourceSize": {"w":15,"h":16}
},
"yellowAirport.png":
{
	"frame": {"x":0,"y":360,"w":15,"h":15},
	"rotated": false,
	"trimmed": false,
	"spriteSourceSize": {"x":0,"y":0,"w":15,"h":15},
	"sourceSize": {"w":15,"h":15}
},
"yellowCity.png":
{
	"frame": {"x":15,"y":375,"w":15,"h":15},
	"rotated": false,
	"trimmed": false,
	"spriteSourceSize": {"x":0,"y":0,"w":15,"h":15},
	"sourceSize": {"w":15,"h":15}
},
"yellowFactory.png":
{
	"frame": {"x":15,"y":390,"w":15,"h":15},
	"rotated": false,
	"trimmed": false,
	"spriteSourceSize": {"x":0,"y":0,"w":15,"h":15},
	"sourceSize": {"w":15,"h":15}
},
"yellowHabor.png":
{
	"frame": {"x":0,"y":390,"w":15,"h":15},
	"rotated": false,
	"trimmed": false,
	"spriteSourceSize": {"x":0,"y":0,"w":15,"h":15},
	"sourceSize": {"w":15,"h":15}
},
"yellowMainCity.png":
{
	"frame": {"x":0,"y":1162,"w":15,"h":30},
	"rotated": false,
	"trimmed": false,
	"spriteSourceSize": {"x":0,"y":0,"w":15,"h":30},
	"sourceSize": {"w":15,"h":30}
},
"yellowSnowAirport.png":
{
	"frame": {"x":0,"y":375,"w":15,"h":15},
	"rotated": false,
	"trimmed": false,
	"spriteSourceSize": {"x":0,"y":0,"w":15,"h":15},
	"sourceSize": {"w":15,"h":15}
},
"yellowSnowCity.png":
{
	"frame": {"x":15,"y":360,"w":15,"h":15},
	"rotated": false,
	"trimmed": false,
	"spriteSourceSize": {"x":0,"y":0,"w":15,"h":15},
	"sourceSize": {"w":15,"h":15}
},
"yellowSnowFactory.png":
{
	"frame": {"x":15,"y":345,"w":15,"h":15},
	"rotated": false,
	"trimmed": false,
	"spriteSourceSize": {"x":0,"y":0,"w":15,"h":15},
	"sourceSize": {"w":15,"h":15}
},
"yellowSnowHabor.png":
{
	"frame": {"x":0,"y":345,"w":15,"h":15},
	"rotated": false,
	"trimmed": false,
	"spriteSourceSize": {"x":0,"y":0,"w":15,"h":15},
	"sourceSize": {"w":15,"h":15}
},
"yellowSnowMainCity.png":
{
	"frame": {"x":0,"y":1252,"w":15,"h":30},
	"rotated": false,
	"trimmed": false,
	"spriteSourceSize": {"x":0,"y":0,"w":15,"h":30},
	"sourceSize": {"w":15,"h":30}
}},
"meta": {
	"app": "http://www.codeandweb.com/texturepacker",
	"version": "1.0",
	"image": "terrain.png",
	"format": "RGBA8888",
	"size": {"w":30,"h":1282},
	"scale": "1",
	"smartupdate": "$TexturePacker:SmartUpdate:13b03607e0cf95e3b32a5ac1677eaecf:5ec25e2b190c334383f4ff10184a097b:a52c91d73586a2a634ceb55ad22f4949$"
}
}
